setup.py
sphinx_amazonjp_embed/__init__.py
sphinx_amazonjp_embed/amazonjp.py
sphinx_amazonjp_embed/errors.py
sphinx_amazonjp_embed/url.py
sphinx_amazonjp_embed.egg-info/PKG-INFO
sphinx_amazonjp_embed.egg-info/SOURCES.txt
sphinx_amazonjp_embed.egg-info/dependency_links.txt
sphinx_amazonjp_embed.egg-info/requires.txt
sphinx_amazonjp_embed.egg-info/top_level.txt
test/test_url.py